nvflare/__init__.py
nvflare/_version.py
nvflare/cli.py
nvflare/cli_exception.py
nvflare/cli_unknown_cmd_exception.py
nvflare/apis/__init__.py
nvflare/apis/analytix.py
nvflare/apis/app_deployer_spec.py
nvflare/apis/app_validation.py
nvflare/apis/aux_spec.py
nvflare/apis/client.py
nvflare/apis/client_engine_spec.py
nvflare/apis/controller_spec.py
nvflare/apis/dxo.py
nvflare/apis/dxo_filter.py
nvflare/apis/engine_spec.py
nvflare/apis/event_type.py
nvflare/apis/executor.py
nvflare/apis/filter.py
nvflare/apis/fl_component.py
nvflare/apis/fl_constant.py
nvflare/apis/fl_context.py
nvflare/apis/fl_exception.py
nvflare/apis/fl_snapshot.py
nvflare/apis/job_def.py
nvflare/apis/job_def_manager_spec.py
nvflare/apis/job_launcher_spec.py
nvflare/apis/job_meta_validator_spec.py
nvflare/apis/job_scheduler_spec.py
nvflare/apis/operator_spec.py
nvflare/apis/overseer_spec.py
nvflare/apis/persistable.py
nvflare/apis/resource_manager_spec.py
nvflare/apis/server_engine_spec.py
nvflare/apis/shareable.py
nvflare/apis/signal.py
nvflare/apis/state_persistor.py
nvflare/apis/storage.py
nvflare/apis/streaming.py
nvflare/apis/wf_comm_spec.py
nvflare/apis/workspace.py
nvflare/apis/impl/__init__.py
nvflare/apis/impl/any_relay_manager.py
nvflare/apis/impl/bcast_manager.py
nvflare/apis/impl/controller.py
nvflare/apis/impl/job_def_manager.py
nvflare/apis/impl/send_manager.py
nvflare/apis/impl/seq_relay_manager.py
nvflare/apis/impl/task_controller.py
nvflare/apis/impl/task_manager.py
nvflare/apis/impl/wf_comm_client.py
nvflare/apis/impl/wf_comm_server.py
nvflare/apis/utils/__init__.py
nvflare/apis/utils/analytix_utils.py
nvflare/apis/utils/fl_context_utils.py
nvflare/apis/utils/format_check.py
nvflare/apis/utils/job_utils.py
nvflare/apis/utils/reliable_message.py
nvflare/apis/utils/task_utils.py
nvflare/apis/utils/decomposers/__init__.py
nvflare/apis/utils/decomposers/flare_decomposers.py
nvflare/app_common/__init__.py
nvflare/app_common/app_constant.py
nvflare/app_common/app_event_type.py
nvflare-2.6.2.dist-info/licenses/LICENSE
nvflare-2.6.2.dist-info/METADATA
nvflare-2.6.2.dist-info/WHEEL
nvflare-2.6.2.dist-info/entry_points.txt
nvflare-2.6.2.dist-info/top_level.txt
nvflare-2.6.2.dist-info/zip-safe
nvflare-2.6.2.dist-info/RECORD
